<database>
  <name>PRIDE Archive</name>
  <description/>
  <release>3</release>
  <release_date>2015-10-5</release_date>
  <entry_count>1</entry_count>
  <entries>
    <entry id="GPM32010008451">
      <name><%%></name>
      <description>"TRANCHE KEY: VnFzDb1JmH6ghvMP0YMcQbggv8nsuMirg9eRFEGjSCRWkm+aHqumS7Aj4D8ybtVIh5WhFszAgrqmcXLLWDjlhWQ/nQ4AAAAAAABbRg== Original folder: CID_DATA, data file: MScDB_HUMAN_PLACENTA_CID_bH1_1_2_575_800_10_01_587_d_1_mgfrecal23.mgf. From Tranche: {{i}}Post-delivery human placenta from a healthy female.{{/i}}"</description>
      </cross_references>
      <additional_fields>
        <field name="omics_type">Proteomics</field>
        <field name="repository">GPMDB</field>
        <field name="instrument_platform">Instrument</field>
        <field name="disease">Not available</field>
        <field name="species">human_female, Human_adenovirus_54, Human_adenovirus_A, Human_adenovirus_B, Human_adenovirus_C, Human_adenovirus_D, Human_adenovirus_E, Human_adenovirus_F, Human_adenovirus_G, Human_astrovirus, Human_bocavirus, Human_bocavirus_2, Human_bocavirus_3, Human_bocavirus_4, Human_coronavirus_229E, Human_coronavirus_HKU1, Human_coronavirus_NL63, Human_coronavirus_OC43, Human_cosavirus_A, Human_cosavirus_B, Human_cosavirus_D, Human_cosavirus_E, Human_enteric_coronavirus_4408, Human_enterovirus_100, Human_enterovirus_A, Human_enterovirus_B, Human_enterovirus_C, Human_enterovirus_D, Human_erythrovirus_V9, Human_herpesvirus_1, Human_herpesvirus_2, Human_herpesvirus_3, Human_herpesvirus_4_type_1, Human_herpesvirus_4_type_2, Human_herpesvirus_5, Human_herpesvirus_6A, Human_herpesvirus_6B, Human_herpesvirus_7, Human_herpesvirus_8_type_P, Human_immunodeficiency_virus_1, Human_immunodeficiency_virus_2, Human_metapneumovirus, Human_papillomavirus_FA75_KI88_03, Human_papillomavirus_RTRX7, Human_papillomavirus_type_10, Human_papillomavirus_type_100, Human_papillomavirus_type_101, Human_papillomavirus_type_103, Human_papillomavirus_type_104, Human_papillomavirus_type_105, Human_papillomavirus_type_108, Human_papillomavirus_type_109, Human_papillomavirus_type_112, Human_papillomavirus_type_113, Human_papillomavirus_type_16, Human_papillomavirus_type_24, Human_papillomavirus_type_26, Human_papillomavirus_type_32, Human_papillomavirus_type_34, Human_papillomavirus_type_4, Human_papillomavirus_type_41, Human_papillomavirus_type_48, Human_papillomavirus_type_49, Human_papillomavirus_type_5, Human_papillomavirus_type_50, Human_papillomavirus_type_53, Human_papillomavirus_type_60, Human_papillomavirus_type_63, Human_papillomavirus_type_6b, Human_papillomavirus_type_7, Human_papillomavirus_type_71, Human_papillomavirus_type_88, Human_papillomavirus_type_9, Human_papillomavirus_type_92, Human_papillomavirus_type_96, Human_papillomavirus_type_98, Human_papillomavirus_type_99, Human_papillomavirus___1, Human_papillomavirus___18, Human_papillomavirus___2, Human_papillomavirus___54, Human_papillomavirus___61, Human_papillomavirus___cand90, Human_parainfluenza_virus_1, Human_parainfluenza_virus_2, Human_parainfluenza_virus_3, Human_parechovirus, Human_parvovirus_4, Human_parvovirus_B19, Human_picobirnavirus, Human_respiratory_syncytial_virus, Human_rhinovirus_A, Human_rhinovirus_B, Human_rhinovirus_C, Human_TMEV_like_cardiovirus, Human_T_lymphotropic_virus_1, Human_T_lymphotropic_virus_2, Human_T_lymphotropic_virus_4</field>
        <field name="publication">Not available</field>
        <field name="brenda_tissue">Not available</field>
        <field name="cell_type">Not available</field>
        <field name="submitter">Hahne H, et al.</field>
        <field name="submitter_mail">hahnew@zw.tum.de</field>
        <field name="submitter_affiliation">Technische Universitaet Muenchen</field>
        <field name="model">http://gpmdb.thegpm.org/~/dblist_gpmnum/gpmnum=GPM32010008451</field>
        <field name="model">http://gpmdb.thegpm.org/~/dblist_gpmnum/gpmnum=GPM32010008470</field>
        <field name="model">http://gpmdb.thegpm.org/~/dblist_gpmnum/gpmnum=GPM32010008520</field>
        <field name="model">http://gpmdb.thegpm.org/~/dblist_gpmnum/gpmnum=GPM32010008475</field>
        <field name="model">http://gpmdb.thegpm.org/~/dblist_gpmnum/gpmnum=GPM32010008504</field>
        <field name="model">http://gpmdb.thegpm.org/~/dblist_gpmnum/gpmnum=GPM32010008481</field>
        <field name="model">http://gpmdb.thegpm.org/~/dblist_gpmnum/gpmnum=GPM32010008489</field>
        <field name="model">http://gpmdb.thegpm.org/~/dblist_gpmnum/gpmnum=GPM32010008449</field>
        <field name="model">http://gpmdb.thegpm.org/~/dblist_gpmnum/gpmnum=GPM32010008473</field>
        <field name="model">http://gpmdb.thegpm.org/~/dblist_gpmnum/gpmnum=GPM32010008515</field>
        <field name="model">http://gpmdb.thegpm.org/~/dblist_gpmnum/gpmnum=GPM32010008488</field>
        <field name="model">http://gpmdb.thegpm.org/~/dblist_gpmnum/gpmnum=GPM32010008414</field>
        <field name="model">http://gpmdb.thegpm.org/~/dblist_gpmnum/gpmnum=GPM32010008508</field>
        <field name="model">http://gpmdb.thegpm.org/~/dblist_gpmnum/gpmnum=GPM32010008494</field>
        <field name="model">http://gpmdb.thegpm.org/~/dblist_gpmnum/gpmnum=GPM32010008428</field>
        <field name="model">http://gpmdb.thegpm.org/~/dblist_gpmnum/gpmnum=GPM32010008524</field>
        <field name="model">http://gpmdb.thegpm.org/~/dblist_gpmnum/gpmnum=GPM32010008499</field>
        <field name="model">http://gpmdb.thegpm.org/~/dblist_gpmnum/gpmnum=GPM32010008433</field>
        <field name="model">http://gpmdb.thegpm.org/~/dblist_gpmnum/gpmnum=GPM32010008436</field>
        <field name="model">http://gpmdb.thegpm.org/~/dblist_gpmnum/gpmnum=GPM32010008502</field>
        <field name="model">http://gpmdb.thegpm.org/~/dblist_gpmnum/gpmnum=GPM32010008507</field>
        <field name="model">http://gpmdb.thegpm.org/~/dblist_gpmnum/gpmnum=GPM32010008441</field>
        <field name="model">http://gpmdb.thegpm.org/~/dblist_gpmnum/gpmnum=GPM32010008460</field>
        <field name="model">http://gpmdb.thegpm.org/~/dblist_gpmnum/gpmnum=GPM32010008523</field>
        <field name="model">http://gpmdb.thegpm.org/~/dblist_gpmnum/gpmnum=GPM32010008476</field>
        <field name="model">http://gpmdb.thegpm.org/~/dblist_gpmnum/gpmnum=GPM32010008447</field>
        <field name="model">http://gpmdb.thegpm.org/~/dblist_gpmnum/gpmnum=GPM32010008506</field>
        <field name="model">http://gpmdb.thegpm.org/~/dblist_gpmnum/gpmnum=GPM32010008461</field>
        <field name="model">http://gpmdb.thegpm.org/~/dblist_gpmnum/gpmnum=GPM32010008519</field>
        <field name="model">http://gpmdb.thegpm.org/~/dblist_gpmnum/gpmnum=GPM32010008429</field>
        <field name="model">http://gpmdb.thegpm.org/~/dblist_gpmnum/gpmnum=GPM32010008458</field>
        <field name="model">http://gpmdb.thegpm.org/~/dblist_gpmnum/gpmnum=GPM32010008431</field>
        <field name="model">http://gpmdb.thegpm.org/~/dblist_gpmnum/gpmnum=GPM32010008421</field>
        <field name="model">http://gpmdb.thegpm.org/~/dblist_gpmnum/gpmnum=GPM32010008493</field>
        <field name="model">http://gpmdb.thegpm.org/~/dblist_gpmnum/gpmnum=GPM32010008457</field>
        <field name="model">http://gpmdb.thegpm.org/~/dblist_gpmnum/gpmnum=GPM32010008530</field>
        <field name="model">http://gpmdb.thegpm.org/~/dblist_gpmnum/gpmnum=GPM32010008424</field>
        <field name="model">http://gpmdb.thegpm.org/~/dblist_gpmnum/gpmnum=GPM32010008430</field>
        <field name="model">http://gpmdb.thegpm.org/~/dblist_gpmnum/gpmnum=GPM32010008462</field>
        <field name="model">http://gpmdb.thegpm.org/~/dblist_gpmnum/gpmnum=GPM32010008445</field>
        <field name="model">http://gpmdb.thegpm.org/~/dblist_gpmnum/gpmnum=GPM32010008527</field>
        <field name="model">http://gpmdb.thegpm.org/~/dblist_gpmnum/gpmnum=GPM32010008505</field>
        <field name="model">http://gpmdb.thegpm.org/~/dblist_gpmnum/gpmnum=GPM32010008496</field>
        <field name="model">http://gpmdb.thegpm.org/~/dblist_gpmnum/gpmnum=GPM32010008437</field>
        <field name="model">http://gpmdb.thegpm.org/~/dblist_gpmnum/gpmnum=GPM32010008455</field>
        <field name="model">http://gpmdb.thegpm.org/~/dblist_gpmnum/gpmnum=GPM32010008420</field>
        <field name="model">http://gpmdb.thegpm.org/~/dblist_gpmnum/gpmnum=GPM32010008440</field>
        <field name="model">http://gpmdb.thegpm.org/~/dblist_gpmnum/gpmnum=GPM32010008526</field>
        <field name="model">http://gpmdb.thegpm.org/~/dblist_gpmnum/gpmnum=GPM32010008479</field>
        <field name="model">http://gpmdb.thegpm.org/~/dblist_gpmnum/gpmnum=GPM32010008418</field>
        <field name="model">http://gpmdb.thegpm.org/~/dblist_gpmnum/gpmnum=GPM32010008452</field>
        <field name="model">http://gpmdb.thegpm.org/~/dblist_gpmnum/gpmnum=GPM32010008468</field>
        <field name="model">http://gpmdb.thegpm.org/~/dblist_gpmnum/gpmnum=GPM32010008459</field>
        <field name="model">http://gpmdb.thegpm.org/~/dblist_gpmnum/gpmnum=GPM32010008486</field>
        <field name="model">http://gpmdb.thegpm.org/~/dblist_gpmnum/gpmnum=GPM32010008477</field>
        <field name="model">http://gpmdb.thegpm.org/~/dblist_gpmnum/gpmnum=GPM32010008509</field>
        <field name="model">http://gpmdb.thegpm.org/~/dblist_gpmnum/gpmnum=GPM32010008521</field>
        <field name="model">http://gpmdb.thegpm.org/~/dblist_gpmnum/gpmnum=GPM32010008425</field>
        <field name="model">http://gpmdb.thegpm.org/~/dblist_gpmnum/gpmnum=GPM32010008500</field>
        <field name="model">http://gpmdb.thegpm.org/~/dblist_gpmnum/gpmnum=GPM32010008472</field>
        <field name="model">http://gpmdb.thegpm.org/~/dblist_gpmnum/gpmnum=GPM32010008415</field>
        <field name="model">http://gpmdb.thegpm.org/~/dblist_gpmnum/gpmnum=GPM32010008525</field>
        <field name="model">http://gpmdb.thegpm.org/~/dblist_gpmnum/gpmnum=GPM32010008482</field>
        <field name="model">http://gpmdb.thegpm.org/~/dblist_gpmnum/gpmnum=GPM32010008416</field>
        <field name="model">http://gpmdb.thegpm.org/~/dblist_gpmnum/gpmnum=GPM32010008435</field>
        <field name="model">http://gpmdb.thegpm.org/~/dblist_gpmnum/gpmnum=GPM32010008453</field>
        <field name="model">http://gpmdb.thegpm.org/~/dblist_gpmnum/gpmnum=GPM32010008478</field>
        <field name="model">http://gpmdb.thegpm.org/~/dblist_gpmnum/gpmnum=GPM32010008464</field>
        <field name="model">http://gpmdb.thegpm.org/~/dblist_gpmnum/gpmnum=GPM32010008501</field>
        <field name="model">http://gpmdb.thegpm.org/~/dblist_gpmnum/gpmnum=GPM32010008463</field>
        <field name="model">http://gpmdb.thegpm.org/~/dblist_gpmnum/gpmnum=GPM32010008483</field>
        <field name="model">http://gpmdb.thegpm.org/~/dblist_gpmnum/gpmnum=GPM32010008490</field>
        <field name="model">http://gpmdb.thegpm.org/~/dblist_gpmnum/gpmnum=GPM32010008487</field>
        <field name="model">http://gpmdb.thegpm.org/~/dblist_gpmnum/gpmnum=GPM32010008454</field>
        <field name="model">http://gpmdb.thegpm.org/~/dblist_gpmnum/gpmnum=GPM32010008492</field>
        <field name="model">http://gpmdb.thegpm.org/~/dblist_gpmnum/gpmnum=GPM32010008450</field>
        <field name="model">http://gpmdb.thegpm.org/~/dblist_gpmnum/gpmnum=GPM32010008443</field>
        <field name="model">http://gpmdb.thegpm.org/~/dblist_gpmnum/gpmnum=GPM32010008434</field>
        <field name="model">http://gpmdb.thegpm.org/~/dblist_gpmnum/gpmnum=GPM32010008446</field>
        <field name="model">http://gpmdb.thegpm.org/~/dblist_gpmnum/gpmnum=GPM32010008423</field>
        <field name="model">http://gpmdb.thegpm.org/~/dblist_gpmnum/gpmnum=GPM32010008480</field>
        <field name="model">http://gpmdb.thegpm.org/~/dblist_gpmnum/gpmnum=GPM32010008469</field>
        <field name="model">http://gpmdb.thegpm.org/~/dblist_gpmnum/gpmnum=GPM32010008444</field>
        <field name="model">http://gpmdb.thegpm.org/~/dblist_gpmnum/gpmnum=GPM32010008518</field>
        <field name="model">http://gpmdb.thegpm.org/~/dblist_gpmnum/gpmnum=GPM32010008442</field>
        <field name="model">http://gpmdb.thegpm.org/~/dblist_gpmnum/gpmnum=GPM32010008474</field>
        <field name="model">http://gpmdb.thegpm.org/~/dblist_gpmnum/gpmnum=GPM32010008467</field>
        <field name="model">http://gpmdb.thegpm.org/~/dblist_gpmnum/gpmnum=GPM32010008466</field>
        <field name="model">http://gpmdb.thegpm.org/~/dblist_gpmnum/gpmnum=GPM32010008465</field>
        <field name="model">http://gpmdb.thegpm.org/~/dblist_gpmnum/gpmnum=GPM32010008456</field>
        <field name="model">http://gpmdb.thegpm.org/~/dblist_gpmnum/gpmnum=GPM32010008491</field>
        <field name="model">http://gpmdb.thegpm.org/~/dblist_gpmnum/gpmnum=GPM32010008513</field>
        <field name="model">http://gpmdb.thegpm.org/~/dblist_gpmnum/gpmnum=GPM32010008439</field>
        <field name="model">http://gpmdb.thegpm.org/~/dblist_gpmnum/gpmnum=GPM32010008522</field>
        <field name="model">http://gpmdb.thegpm.org/~/dblist_gpmnum/gpmnum=GPM32010008419</field>
        <field name="model">http://gpmdb.thegpm.org/~/dblist_gpmnum/gpmnum=GPM32010008528</field>
        <field name="model">http://gpmdb.thegpm.org/~/dblist_gpmnum/gpmnum=GPM32010008495</field>
        <field name="model">http://gpmdb.thegpm.org/~/dblist_gpmnum/gpmnum=GPM32010008427</field>
        <field name="model">http://gpmdb.thegpm.org/~/dblist_gpmnum/gpmnum=GPM32010008484</field>
        <field name="model">http://gpmdb.thegpm.org/~/dblist_gpmnum/gpmnum=GPM32010008485</field>
        <field name="model">http://gpmdb.thegpm.org/~/dblist_gpmnum/gpmnum=GPM32010008448</field>
        <field name="model">http://gpmdb.thegpm.org/~/dblist_gpmnum/gpmnum=GPM32010008417</field>
        <field name="model">http://gpmdb.thegpm.org/~/dblist_gpmnum/gpmnum=GPM32010008512</field>
        <field name="model">http://gpmdb.thegpm.org/~/dblist_gpmnum/gpmnum=GPM32010008511</field>
        <field name="model">http://gpmdb.thegpm.org/~/dblist_gpmnum/gpmnum=GPM32010008497</field>
        <field name="model">http://gpmdb.thegpm.org/~/dblist_gpmnum/gpmnum=GPM32010008432</field>
        <field name="model">http://gpmdb.thegpm.org/~/dblist_gpmnum/gpmnum=GPM32010008498</field>
        <field name="model">http://gpmdb.thegpm.org/~/dblist_gpmnum/gpmnum=GPM32010008529</field>
        <field name="model">http://gpmdb.thegpm.org/~/dblist_gpmnum/gpmnum=GPM32010008514</field>
        <field name="model">http://gpmdb.thegpm.org/~/dblist_gpmnum/gpmnum=GPM32010008426</field>
        <field name="model">http://gpmdb.thegpm.org/~/dblist_gpmnum/gpmnum=GPM32010008517</field>
        <field name="model">http://gpmdb.thegpm.org/~/dblist_gpmnum/gpmnum=GPM32010008422</field>
        <field name="model">http://gpmdb.thegpm.org/~/dblist_gpmnum/gpmnum=GPM32010008516</field>
        <field name="model">http://gpmdb.thegpm.org/~/dblist_gpmnum/gpmnum=GPM32010008510</field>
        <field name="model">http://gpmdb.thegpm.org/~/dblist_gpmnum/gpmnum=GPM32010008503</field>
        <field name="model">http://gpmdb.thegpm.org/~/dblist_gpmnum/gpmnum=GPM32010008531</field>
        <field name="model">http://gpmdb.thegpm.org/~/dblist_gpmnum/gpmnum=GPM32010008471</field>
        <field name="model">http://gpmdb.thegpm.org/~/dblist_gpmnum/gpmnum=GPM32010008438</field>
      </additional_fields>
    </entry>
  </entries>
</database>
