<database>
  <name>PRIDE Archive</name>
  <description/>
  <release>3</release>
  <release_date>2015-10-12</release_date>
  <entry_count>1</entry_count>
  <entries>
    <entry id="GPM32010006174">
      <name>LC-MS of 12 OGE Fractions Quiescense S. Pombe</name>
      <description>TRANCHE KEY: 1gNlqHIUVaHU8S8yqpR8tvKvq6m0jySALyTlBxte1YvIo/N8IPXlMsgRKu2ZTgsdPHPG0Z0jrrWtiDJ1CEXSb/fQY0kAAAAAAAACHg== Original data file: A11-05271.mzXML.</description>
      <cross_references>
      <ref dbkey="MSV000077236" dbname="massive"/>
      </cross_references>
      <dates>
        <date type="submission" value="xx-xx-xx"/>
      </dates>
      <additional_fields>
        <field name="omics_type">Proteomics</field>
        <field name="repository">GPMDB</field>
        <field name="instrument_platform">Instrument</field>
        <field name="disease">Not available</field>
        <field name="species">s_pombe</field>
        <field name="publication">Not available</field>
        <field name="brenda_tissue">Not available</field>
        <field name="cell_type">Not available</field>
        <field name="submitter">Schmidt A, et al.</field>
        <field name="submitter_mail">alex.schmidt@unibas.ch</field>
        <field name="submitter_affiliation">University of Basel</field>
        <field name="model">http://gpmdb.thegpm.org/~/dblist_gpmnum/gpmnum=GPM32010006178</field>
        <field name="model">http://gpmdb.thegpm.org/~/dblist_gpmnum/gpmnum=GPM32010006179</field>
        <field name="model">http://gpmdb.thegpm.org/~/dblist_gpmnum/gpmnum=GPM32010006175</field>
        <field name="model">http://gpmdb.thegpm.org/~/dblist_gpmnum/gpmnum=GPM32010006185</field>
        <field name="model">http://gpmdb.thegpm.org/~/dblist_gpmnum/gpmnum=GPM32010006182</field>
        <field name="model">http://gpmdb.thegpm.org/~/dblist_gpmnum/gpmnum=GPM32010006183</field>
        <field name="model">http://gpmdb.thegpm.org/~/dblist_gpmnum/gpmnum=GPM32010006184</field>
        <field name="model">http://gpmdb.thegpm.org/~/dblist_gpmnum/gpmnum=GPM32010006186</field>
        <field name="model">http://gpmdb.thegpm.org/~/dblist_gpmnum/gpmnum=GPM32010006176</field>
        <field name="model">http://gpmdb.thegpm.org/~/dblist_gpmnum/gpmnum=GPM32010006177</field>
        <field name="model">http://gpmdb.thegpm.org/~/dblist_gpmnum/gpmnum=GPM32010006180</field>
        <field name="model">http://gpmdb.thegpm.org/~/dblist_gpmnum/gpmnum=GPM32010006174</field>
      </additional_fields>
    </entry>
  </entries>
</database>
