<database>
  <name>PRIDE Archive</name>
  <description/>
  <release>3</release>
  <release_date>2015-10-11</release_date>
  <entry_count>1</entry_count>
  <entries>
    <entry id="GPM10100161939">
      <name>PAe000425_mzXML_200905031549</name>
      <description>TRANCHE KEY: 41MjPxGcJtP4acNfDaz0DFBO10HhfqdFPPpxh8CTGOMeHQbsrlvRbF2EEK/CFqix6/gvVyN90oGg3bpDpGQKKXXae4MAAAAAAAAA8w==  PeptideAtlas ID: PAe000425.</description>
      <cross_references></cross_references>
      <dates>
        <date type="submission" value="xx-xx-xx"/>
      </dates>
      <additional_fields>
        <field name="omics_type">Proteomics</field>
        <field name="repository">GPMDB</field>
        <field name="instrument_platform">Instrument</field>
        <field name="disease">Not available</field>
        <field name="species">worm</field>
        <field name="publication">Not available</field>
        <field name="brenda_tissue">Not available</field>
        <field name="cell_type">Not available</field>
        <field name="submitter">Z. Sun</field>
        <field name="submitter_mail">Not available</field>
        <field name="submitter_affiliation">Institute for Systems Biology</field>
        <field name="model">http://gpmdb.thegpm.org/~/dblist_gpmnum/gpmnum=GPM10100161943</field>
        <field name="model">http://gpmdb.thegpm.org/~/dblist_gpmnum/gpmnum=GPM10100161963</field>
        <field name="model">http://gpmdb.thegpm.org/~/dblist_gpmnum/gpmnum=GPM10100161915</field>
        <field name="model">http://gpmdb.thegpm.org/~/dblist_gpmnum/gpmnum=GPM10100161945</field>
        <field name="model">http://gpmdb.thegpm.org/~/dblist_gpmnum/gpmnum=GPM10100161948</field>
        <field name="model">http://gpmdb.thegpm.org/~/dblist_gpmnum/gpmnum=GPM10100161957</field>
        <field name="model">http://gpmdb.thegpm.org/~/dblist_gpmnum/gpmnum=GPM10100161946</field>
        <field name="model">http://gpmdb.thegpm.org/~/dblist_gpmnum/gpmnum=GPM10100161953</field>
        <field name="model">http://gpmdb.thegpm.org/~/dblist_gpmnum/gpmnum=GPM10100161955</field>
        <field name="model">http://gpmdb.thegpm.org/~/dblist_gpmnum/gpmnum=GPM10100161952</field>
        <field name="model">http://gpmdb.thegpm.org/~/dblist_gpmnum/gpmnum=GPM10100161936</field>
        <field name="model">http://gpmdb.thegpm.org/~/dblist_gpmnum/gpmnum=GPM10100161922</field>
        <field name="model">http://gpmdb.thegpm.org/~/dblist_gpmnum/gpmnum=GPM10100161958</field>
        <field name="model">http://gpmdb.thegpm.org/~/dblist_gpmnum/gpmnum=GPM10100161949</field>
        <field name="model">http://gpmdb.thegpm.org/~/dblist_gpmnum/gpmnum=GPM10100161941</field>
        <field name="model">http://gpmdb.thegpm.org/~/dblist_gpmnum/gpmnum=GPM10100161926</field>
        <field name="model">http://gpmdb.thegpm.org/~/dblist_gpmnum/gpmnum=GPM10100161928</field>
        <field name="model">http://gpmdb.thegpm.org/~/dblist_gpmnum/gpmnum=GPM10100161961</field>
        <field name="model">http://gpmdb.thegpm.org/~/dblist_gpmnum/gpmnum=GPM10100161929</field>
        <field name="model">http://gpmdb.thegpm.org/~/dblist_gpmnum/gpmnum=GPM10100161918</field>
        <field name="model">http://gpmdb.thegpm.org/~/dblist_gpmnum/gpmnum=GPM10100161937</field>
        <field name="model">http://gpmdb.thegpm.org/~/dblist_gpmnum/gpmnum=GPM10100161930</field>
        <field name="model">http://gpmdb.thegpm.org/~/dblist_gpmnum/gpmnum=GPM10100161923</field>
        <field name="model">http://gpmdb.thegpm.org/~/dblist_gpmnum/gpmnum=GPM10100161944</field>
        <field name="model">http://gpmdb.thegpm.org/~/dblist_gpmnum/gpmnum=GPM10100161933</field>
        <field name="model">http://gpmdb.thegpm.org/~/dblist_gpmnum/gpmnum=GPM10100161956</field>
        <field name="model">http://gpmdb.thegpm.org/~/dblist_gpmnum/gpmnum=GPM10100161962</field>
        <field name="model">http://gpmdb.thegpm.org/~/dblist_gpmnum/gpmnum=GPM10100161938</field>
        <field name="model">http://gpmdb.thegpm.org/~/dblist_gpmnum/gpmnum=GPM10100161931</field>
        <field name="model">http://gpmdb.thegpm.org/~/dblist_gpmnum/gpmnum=GPM10100161917</field>
        <field name="model">http://gpmdb.thegpm.org/~/dblist_gpmnum/gpmnum=GPM10100161940</field>
        <field name="model">http://gpmdb.thegpm.org/~/dblist_gpmnum/gpmnum=GPM10100161950</field>
        <field name="model">http://gpmdb.thegpm.org/~/dblist_gpmnum/gpmnum=GPM10100161942</field>
        <field name="model">http://gpmdb.thegpm.org/~/dblist_gpmnum/gpmnum=GPM10100161925</field>
        <field name="model">http://gpmdb.thegpm.org/~/dblist_gpmnum/gpmnum=GPM10100161916</field>
        <field name="model">http://gpmdb.thegpm.org/~/dblist_gpmnum/gpmnum=GPM10100161935</field>
        <field name="model">http://gpmdb.thegpm.org/~/dblist_gpmnum/gpmnum=GPM10100161959</field>
        <field name="model">http://gpmdb.thegpm.org/~/dblist_gpmnum/gpmnum=GPM10100161954</field>
        <field name="model">http://gpmdb.thegpm.org/~/dblist_gpmnum/gpmnum=GPM10100161921</field>
        <field name="model">http://gpmdb.thegpm.org/~/dblist_gpmnum/gpmnum=GPM10100161927</field>
        <field name="model">http://gpmdb.thegpm.org/~/dblist_gpmnum/gpmnum=GPM10100161960</field>
        <field name="model">http://gpmdb.thegpm.org/~/dblist_gpmnum/gpmnum=GPM10100161920</field>
        <field name="model">http://gpmdb.thegpm.org/~/dblist_gpmnum/gpmnum=GPM10100161919</field>
        <field name="model">http://gpmdb.thegpm.org/~/dblist_gpmnum/gpmnum=GPM10100161939</field>
      </additional_fields>
    </entry>
  </entries>
</database>
